<CRDoc>[Congressional Record Volume <volume>160</volume>, Number <number>37</number> (<weekday>Wednesday</weekday>, <month>March</month> <day>5</day>, <year>2014</year>)]
[<chamber>Extensions</chamber> of Remarks]
[Page <pages>E306</pages>]
<congress>113</congress>
<session>2</session>
                          <document_title>PERSONAL EXPLANATION</document_title>
                     <title>HON. ERIC A. ``RICK'' CRAWFORD</title>
                              <title>of arkansas</title>
                    <title>in the house of representatives</title>
                        <title>Wednesday, March 5, 2014</title>
  <speaker name="Mr. CRAWFORD">Mr. CRAWFORD</speaker>. <speaking name="Mr. CRAWFORD">Mr. Speaker, on Tuesday, March 4th, 2014 I was 
inadvertently detained on rollcall Votes 91 and 92. Had I been present 
to vote I would have voted ``yes'' on both.</speaking>
</CRDoc>